[
  {
    "name": "Luke Avers",
    "hometown": "Woodville, OH",
    "aliases": ["Lukas Avers"],
    "image": "/img/2025-headshots/luke-avers.webp",
    "roster": { "number": "#1", "position": "GK", "appearances": 3 }
  },
  {
    "name": "Collin Biehler",
    "hometown": "Oak Harbor, OH",
    "image": "/img/2026-men-headshots/collin-biehler.jpg",
    "roster": { "number": "#17", "position": "GK", "appearances": 14 }
  },
  {
    "name": "Kaiden Hawes",
    "hometown": "Oregon, OH",
    "image": "/img/2026-men-headshots/kaiden-hawes.jpg",
    "roster": { "number": "#3", "position": "CB", "appearances": 6 }
  },
  {
    "name": "Yoni Moralez",
    "hometown": "Willard, OH",
    "image": "/img/2025-headshots/yoni-moralez.webp",
    "roster": { "number": "#4", "position": "CB", "appearances": 7 }
  },
  {
    "name": "Grant Miller",
    "hometown": "Tiffin, OH",
    "image": "/img/2025-headshots/grant-miller.webp",
    "roster": { "number": "#5", "position": "CB", "appearances": 11 }
  },
  {
    "name": "Christian Heidl",
    "hometown": "Huron, OH",
    "aliases": ["Chris Heidl"],
    "image": "/img/2025-headshots/chris-heidl.webp",
    "roster": { "number": "#6", "position": "CM", "appearances": 10 }
  },
  {
    "name": "Blake Kubasak",
    "hometown": "Lorain, OH",
    "image": "/img/2025-headshots/blake-kubasak.webp",
    "roster": { "number": "#8", "position": "LWB/LB", "appearances": 14 }
  },
  {
    "name": "Jon Slay",
    "hometown": "Sandusky, OH",
    "image": "/img/2026-men-headshots/jon-slay.jpg",
    "roster": { "number": "#9", "position": "ST/LW", "appearances": 15 }
  },
  {
    "name": "Brock Harman",
    "hometown": "Avon, OH",
    "image": "/img/2025-headshots/brock-harman.webp",
    "roster": { "number": "#10", "position": "ST/CAM", "appearances": 9 }
  },
  {
    "name": "Jonah Main",
    "hometown": "Berlin Heights, OH",
    "image": "/img/2026-men-headshots/jonah-main.jpg",
    "roster": { "number": "#11", "position": "CM", "appearances": 17 }
  },
  {
    "name": "Reggie Johnson",
    "hometown": "Lorain, OH",
    "image": "/img/2025-headshots/reggie-johnson.webp",
    "roster": { "number": "#12", "position": "ST/RW", "appearances": 17 }
  },
  {
    "name": "Jordan Dankert",
    "hometown": "Rossford, OH",
    "roster": { "number": "#13", "position": "GK", "appearances": 5 }
  },
  {
    "name": "Maximus Parsell",
    "hometown": "Sycamore, OH",
    "image": "/img/2026-men-headshots/maximus-parsell.jpg",
    "roster": { "number": "#14", "position": "CM/CAM", "appearances": 6 }
  },
  {
    "name": "Jack Ramey",
    "hometown": "Richmond, VA",
    "image": "/img/2026-men-headshots/jack-ramey.jpg",
    "roster": { "number": "#15", "position": "CM", "appearances": 6 }
  },
  {
    "name": "Noah Clapsaddle",
    "hometown": "Oak Harbor, OH",
    "image": "/img/2026-men-headshots/noah-clapsaddle.jpg",
    "roster": { "number": "#16", "position": "LB/RB", "appearances": 14 }
  },
  {
    "name": "Ayden Adams",
    "hometown": "Tiffin, OH",
    "image": "/img/2026-men-headshots/ayden-adams.jpg",
    "roster": { "number": "#18", "position": "LW/LWB", "appearances": 6 }
  },
  {
    "name": "Cohen Hawes",
    "hometown": "Oregon, OH",
    "image": "/img/2026-men-headshots/cohen-hawes.jpg",
    "roster": { "number": "#19", "position": "LB/RB", "appearances": 5 }
  },
  {
    "name": "Kenny Alejandro",
    "hometown": "Willard, OH",
    "image": "/img/2025-headshots/kenny-alejandro.webp",
    "roster": { "number": "#21", "position": "LW/LWB", "appearances": 7 }
  },
  {
    "name": "Coen Steinmetz",
    "hometown": "Tiffin, OH",
    "image": "/img/2026-men-headshots/coen-steinmetz.jpg",
    "roster": { "number": "#22", "position": "LB/RB", "appearances": 17 }
  },
  {
    "name": "Simon Joseph",
    "hometown": "Perrysburg, OH",
    "image": "/img/2025-headshots/simon-joseph.webp",
    "roster": { "number": "#77", "position": "ST", "appearances": 9 }
  },
  {
    "name": "Erik Rangel Negrete",
    "hometown": "Norwalk, OH",
    "image": "/img/2026-men-headshots/erik-rangel-negrete.jpg",
    "roster": { "number": "#7", "position": "CM/CAM", "appearances": 3 }
  },
  {
    "name": "Carter Jones",
    "hometown": "Milan, OH",
    "image": "/img/2026-men-headshots/carter-jones.jpg",
    "roster": { "number": "#21", "position": "FWD", "appearances": 6 }
  },
  {
    "name": "Jackson Gray",
    "hometown": "Vermilion, OH",
    "image": "/img/2026-men-headshots/jackson-gray.jpg",
    "roster": { "number": "#TBD", "position": "CB", "appearances": 3 }
  },
  {
    "name": "Joseph Judge",
    "hometown": "Oak Harbor, OH",
    "roster": { "number": "#TBD", "position": "CB", "appearances": 5 }
  },
  {
    "name": "Ryan Graber",
    "hometown": "Amherst, OH",
    "image": "/img/2026-men-headshots/ryan-graber.jpg",
    "roster": { "number": "#TBD", "position": "LB/RB", "appearances": 6 }
  },
  {
    "name": "Alex Davidson",
    "hometown": "Norwalk, OH",
    "image": "/img/2025-headshots/alex-davidson.webp",
    "roster": { "number": "#18", "position": "CAM", "appearances": 7 }
  },
  {
    "name": "Kevin Alejandro",
    "hometown": "Plymouth, OH",
    "image": "/img/2025-headshots/kevin-alejandro.webp",
    "roster": { "number": "#23", "position": "LW/LWB", "appearances": 5 }
  },
  {
    "name": "Luis Alvarado",
    "hometown": "Willard, OH",
    "image": "/img/2025-headshots/luis-alvarado.webp",
    "roster": { "number": "#3", "position": "RW", "appearances": 10 }
  },
  {
    "name": "Kelly Itito",
    "hometown": "Allen Park, MI",
    "image": "/img/2025-headshots/kelly-itito.webp",
    "roster": { "number": "#10", "position": "CDM", "appearances": 8 }
  },
  {
    "name": "Connor Hauger",
    "hometown": "Fremont, OH",
    "image": "/img/2025-headshots/connor-hauger.webp",
    "roster": { "number": "#12", "position": "CB", "appearances": 10 }
  },
  {
    "name": "Kylen Coopshaw",
    "hometown": "Tiffin, OH",
    "aliases": ["Kylan Coopshaw"],
    "image": "/img/2025-headshots/kylan-coopshaw.webp",
    "roster": { "number": "#7", "position": "LB/RB", "appearances": 5 }
  },
  {
    "name": "Bryan Gerber",
    "hometown": "Tiffin, OH",
    "image": "/img/2025-headshots/bryan-gerber.webp",
    "roster": { "number": "#14", "position": "CB", "appearances": 4 }
  },
  {
    "name": "Phil Kirimi",
    "hometown": "Oak Harbor, OH",
    "image": "/img/2026-men-headshots/phil-kirimi.jpg",
    "roster": { "number": "#0", "position": "CB", "appearances": 6 }
  },
  {
    "name": "Zane Gabrielson",
    "hometown": "Tiffin, OH",
    "image": "/img/2025-headshots/zane-gabrielson.webp",
    "roster": { "number": "#19", "position": "RB", "appearances": 5 }
  },
  {
    "name": "Andrew Chwalik",
    "hometown": "Marblehead, OH",
    "image": "/img/2025-headshots/andrew-chwalik.webp"
  },
  {
    "name": "George Villiers",
    "hometown": "Lancing, UK",
    "image": "/img/2025-headshots/george-villiers.webp"
  },
  {
    "name": "Kaden Camp",
    "hometown": "Sandusky, OH",
    "aliases": ["Kaden Kamp"],
    "image": "/img/2026-men-headshots/kaden-camp.jpg",
    "roster": { "number": "#2", "position": "LB/RB", "appearances": 5 }
  },
  {
    "name": "Zoe Turner",
    "hometown": "Northwood, OH",
    "image": "/img/2025-headshots/zoe-turner.webp"
  }
]
